xlpandas/__init__.py
xlpandas-0.1.4.dist-info/LICENSE
xlpandas-0.1.4.dist-info/METADATA
xlpandas-0.1.4.dist-info/WHEEL
xlpandas-0.1.4.dist-info/top_level.txt
xlpandas-0.1.4.dist-info/RECORD
