Metadata-Version: 2.1
Name: xlpandas
Version: 0.1.4
Summary: Read and write xlsx/xlst using pandas/openpyxl while preserving Excel formatting
Home-page: https://github.com/fgassert/xlpandas
Author: Francis Gassert
License: MIT
Platform: UNKNOWN
Classifier: Programming Language :: Python :: 3
Classifier: License :: OSI Approved :: MIT License
Classifier: Operating System :: OS Independent
Requires-Dist: openpyxl
Requires-Dist: pandas
